LICENSE
MANIFEST.in
README.rst
setup.py
django_formsets_bootstrap3.egg-info/PKG-INFO
django_formsets_bootstrap3.egg-info/SOURCES.txt
django_formsets_bootstrap3.egg-info/dependency_links.txt
django_formsets_bootstrap3.egg-info/top_level.txt
easy_formsets_bootstrap/__init__.py
easy_formsets_bootstrap/admin.py
easy_formsets_bootstrap/models.py
easy_formsets_bootstrap/tests.py
easy_formsets_bootstrap/views.py
easy_formsets_bootstrap/templates/form_inlines/all_formsets.html
easy_formsets_bootstrap/templates/form_inlines/all_formsets.html~
easy_formsets_bootstrap/templates/form_inlines/empty_formsets.html
easy_formsets_bootstrap/templates/form_inlines/empty_formsets.html~
easy_formsets_bootstrap/templates/form_inlines/main_form.html
easy_formsets_bootstrap/templates/form_inlines/main_form.html~
easy_formsets_bootstrap/templatetags/__init__.py
easy_formsets_bootstrap/templatetags/form_inlines.py
easy_formsets_bootstrap/templatetags/form_inlines.py~