Metadata-Version: 1.1
Name: django-formsets-bootstrap3
Version: 0.2.2
Summary: A simple Django app for inlines formsets
Home-page: http://github.com/
Author: FireGM
Author-email: dobi@mail.ru
License: BSD Licens
Platform: UNKNOWN
Classifier: Environment :: Web Environment
Classifier: Framework :: Django
Classifier: Intended Audience :: Developers
Classifier: License :: OSI Approved :: BSD License
Classifier: Operating System :: OS Independent
Classifier: Programming Language :: Python
Classifier: Programming Language :: Python :: 3
Classifier: Programming Language :: Python :: 3.2
Classifier: Programming Language :: Python :: 3.3
Classifier: Topic :: Internet :: WWW/HTTP
Classifier: Topic :: Internet :: WWW/HTTP :: Dynamic Content
